bugtrack
