Metadata-Version: 1.0
Name: bugtrack
Version: 0.2.6
Summary: Initial
Home-page: UNKNOWN
Author: Csaba Saranszky
Author-email: alt@256.hu
License: GPL
Platform: UNKNOWN
